{
  "SessionType": "Qualification",
  "RaceType": "Regular",
  "QualType": "Q2",
  "SessionPosition": 2,
  "Date": null,
  "TrackName": "Spain",
  "TrackUniqueName": "barcelona.2021",
  "Drivers": [
    {
      "Driver": {
        "Name": "Waerheall Holloway"
      },
      "RaceNumber": 97,
      "Position": 1,
      "Team": {
        "Name": "Frontier Racing",
        "UniqueName": "frontierracing.2025"
      },
      "SeatType": "Primary",
      "Status": "Ok",
      "TimeInt": 0,
      "GapInt": 0,
      "FastestLapTimeInt": 70623,
      "LapsCount": 0
    },
    {
      "Driver": {
        "Name": "Fernando Alonso"
      },
      "RaceNumber": 14,
      "Position": 2,
      "Team": {
        "Name": "McLaren",
        "UniqueName": "mclaren.2025"
      },
      "SeatType": "Primary",
      "Status": "Ok",
      "TimeInt": 0,
      "GapInt": 0,
      "FastestLapTimeInt": 74241,
      "LapsCount": 5
    },
    {
      "Driver": {
        "Name": "Carlos Sainz"
      },
      "RaceNumber": 55,
      "Position": 3,
      "Team": {
        "Name": "McLaren",
        "UniqueName": "mclaren.2025"
      },
      "SeatType": "Primary",
      "Status": "Ok",
      "TimeInt": 0,
      "GapInt": 0,
      "FastestLapTimeInt": 74260,
      "LapsCount": 5
    },
    {
      "Driver": {
        "Name": "Max Verstappen"
      },
      "RaceNumber": 33,
      "Position": 4,
      "Team": {
        "Name": "Aston Martin",
        "UniqueName": "astonmartin.2025"
      },
      "SeatType": "Primary",
      "Status": "Ok",
      "TimeInt": 0,
      "GapInt": 0,
      "FastestLapTimeInt": 74548,
      "LapsCount": 5
    },
    {
      "Driver": {
        "Name": "Esteban Ocon"
      },
      "RaceNumber": 31,
      "Position": 5,
      "Team": {
        "Name": "Red Bull",
        "UniqueName": "redbull.2025"
      },
      "SeatType": "Primary",
      "Status": "Ok",
      "TimeInt": 0,
      "GapInt": 0,
      "FastestLapTimeInt": 74631,
      "LapsCount": 5
    },
    {
      "Driver": {
        "Name": "Lando Norris"
      },
      "RaceNumber": 4,
      "Position": 6,
      "Team": {
        "Name": "Aston Martin",
        "UniqueName": "astonmartin.2025"
      },
      "SeatType": "Primary",
      "Status": "Ok",
      "TimeInt": 0,
      "GapInt": 0,
      "FastestLapTimeInt": 74672,
      "LapsCount": 5
    },
    {
      "Driver": {
        "Name": "Oscar Piastri"
      },
      "RaceNumber": 81,
      "Position": 7,
      "Team": {
        "Name": "Williams",
        "UniqueName": "williams.2025"
      },
      "SeatType": "Primary",
      "Status": "Ok",
      "TimeInt": 0,
      "GapInt": 0,
      "FastestLapTimeInt": 74818,
      "LapsCount": 5
    },
    {
      "Driver": {
        "Name": "Sergio Perez"
      },
      "RaceNumber": 11,
      "Position": 8,
      "Team": {
        "Name": "Red Bull",
        "UniqueName": "redbull.2025"
      },
      "SeatType": "Primary",
      "Status": "Ok",
      "TimeInt": 0,
      "GapInt": 0,
      "FastestLapTimeInt": 74837,
      "LapsCount": 5
    },
    {
      "Driver": {
        "Name": "Charles Leclerc"
      },
      "RaceNumber": 1,
      "Position": 9,
      "Team": {
        "Name": "Ferrari",
        "UniqueName": "ferrari.2025"
      },
      "SeatType": "Primary",
      "Status": "Ok",
      "TimeInt": 0,
      "GapInt": 0,
      "FastestLapTimeInt": 74923,
      "LapsCount": 5
    },
    {
      "Driver": {
        "Name": "Liam Lawson"
      },
      "RaceNumber": 40,
      "Position": 10,
      "Team": {
        "Name": "Ferrari",
        "UniqueName": "ferrari.2025"
      },
      "SeatType": "Primary",
      "Status": "Ok",
      "TimeInt": 0,
      "GapInt": 0,
      "FastestLapTimeInt": 74978,
      "LapsCount": 5
    },
    {
      "Driver": {
        "Name": "Kimi Antonelli"
      },
      "RaceNumber": 12,
      "Position": 11,
      "Team": {
        "Name": "Haas",
        "UniqueName": "haas.2025"
      },
      "SeatType": "Primary",
      "Status": "Ok",
      "TimeInt": 0,
      "GapInt": 0,
      "FastestLapTimeInt": 75169,
      "LapsCount": 6
    },
    {
      "Driver": {
        "Name": "Alexander Albon"
      },
      "RaceNumber": 23,
      "Position": 12,
      "Team": {
        "Name": "Lotus",
        "UniqueName": "lotus.2025"
      },
      "SeatType": "Primary",
      "Status": "Ok",
      "TimeInt": 0,
      "GapInt": 0,
      "FastestLapTimeInt": 75290,
      "LapsCount": 5
    },
    {
      "Driver": {
        "Name": "Yuki Tsunoda"
      },
      "RaceNumber": 22,
      "Position": 13,
      "Team": {
        "Name": "Mercedes",
        "UniqueName": "mercedes.2025"
      },
      "SeatType": "Primary",
      "Status": "Ok",
      "TimeInt": 0,
      "GapInt": 0,
      "FastestLapTimeInt": 75354,
      "LapsCount": 5
    },
    {
      "Driver": {
        "Name": "Pierre Gasly"
      },
      "RaceNumber": 10,
      "Position": 14,
      "Team": {
        "Name": "Mercedes",
        "UniqueName": "mercedes.2025"
      },
      "SeatType": "Primary",
      "Status": "Ok",
      "TimeInt": 0,
      "GapInt": 0,
      "FastestLapTimeInt": 75463,
      "LapsCount": 6
    },
    {
      "Driver": {
        "Name": "Oliver Bearman"
      },
      "RaceNumber": 87,
      "Position": 15,
      "Team": {
        "Name": "Williams",
        "UniqueName": "williams.2025"
      },
      "SeatType": "Primary",
      "Status": "Ok",
      "TimeInt": 0,
      "GapInt": 0,
      "FastestLapTimeInt": 75953,
      "LapsCount": 6
    }
  ],
  "FastestLapDriver": {
    "Name": "Waerheall Holloway"
  },
  "FastestLapTimeInt": 70623
}